{
  "gate_adr": "0061",
  "g1_passes_of_9": 4,
  "g2_lift_cost_r_vs_ce": 7,
  "g3_edge_preserved": 6,
  "g4_bull_h2_passes": 0,
  "gate1": "PASS",
  "gate2": "PASS",
  "gate3": "PASS",
  "gate4": "PASS",
  "overall": "PASS",
  "pilots": [
    {
      "tag": "CH.1",
      "asset": "btc",
      "period": "20240705_20241231",
      "regime": "2024-H2",
      "ch_metrics": {
        "trades": 43,
        "sharpe": -0.7592271464306704,
        "mdd_pct": 4.585986329656742,
        "final_eq": 9836.809988446586,
        "cost_r": 0.9753201497302671,
        "mc_p5": 9386.818197731469
      },
      "ce_metrics": {
        "trades": 62,
        "sharpe": -2.773013713735254,
        "mdd_pct": 15.198329071137767,
        "final_eq": 8919.857560760056,
        "cost_r": 0.9597181765129299,
        "mc_p5": 7905.403565640286
      },
      "pass_gate1": false,
      "fail_reasons": [
        "Sharpe",
        "MCp5"
      ]
    },
    {
      "tag": "CH.2",
      "asset": "eth",
      "period": "20240705_20241231",
      "regime": "2024-H2",
      "ch_metrics": {
        "trades": 52,
        "sharpe": -1.523907324166006,
        "mdd_pct": 8.363601740274937,
        "final_eq": 9496.938123810607,
        "cost_r": 0.9711405962325235,
        "mc_p5": 8690.50032296701
      },
      "ce_metrics": {
        "trades": 73,
        "sharpe": -1.2496745638950852,
        "mdd_pct": 14.054178472894959,
        "final_eq": 9355.602789306966,
        "cost_r": 0.957598999786637,
        "mc_p5": 8128.843501890267
      },
      "pass_gate1": false,
      "fail_reasons": [
        "Sharpe",
        "MCp5"
      ]
    },
    {
      "tag": "CH.3",
      "asset": "sol",
      "period": "20240705_20241231",
      "regime": "2024-H2",
      "ch_metrics": {
        "trades": 73,
        "sharpe": -0.38505017070095143,
        "mdd_pct": 9.22199409600608,
        "final_eq": 9783.120029854288,
        "cost_r": 0.958765137562883,
        "mc_p5": 8733.749480414193
      },
      "ce_metrics": {
        "trades": 65,
        "sharpe": -1.0937851008401618,
        "mdd_pct": 19.33346137708918,
        "final_eq": 9293.826098099476,
        "cost_r": 0.9610402526213239,
        "mc_p5": 8043.393085175631
      },
      "pass_gate1": false,
      "fail_reasons": [
        "Sharpe",
        "MCp5"
      ]
    },
    {
      "tag": "CH.4",
      "asset": "btc",
      "period": "20250105_20250704",
      "regime": "2025-H1",
      "ch_metrics": {
        "trades": 37,
        "sharpe": 1.6878345964859356,
        "mdd_pct": 1.6690512345348487,
        "final_eq": 10406.584264100899,
        "cost_r": 0.9780625725441316,
        "mc_p5": 9912.946428228644
      },
      "ce_metrics": {
        "trades": 82,
        "sharpe": 0.232894680655545,
        "mdd_pct": 4.080659863919042,
        "final_eq": 10069.713544510152,
        "cost_r": 0.9563996530233912,
        "mc_p5": 9459.907111553586
      },
      "pass_gate1": true,
      "fail_reasons": []
    },
    {
      "tag": "CH.5",
      "asset": "eth",
      "period": "20250105_20250704",
      "regime": "2025-H1",
      "ch_metrics": {
        "trades": 77,
        "sharpe": 0.49689392590955406,
        "mdd_pct": 8.305172182382883,
        "final_eq": 10217.357348770945,
        "cost_r": 0.9609418590223264,
        "mc_p5": 8907.330155542006
      },
      "ce_metrics": {
        "trades": 100,
        "sharpe": 0.5501451396055386,
        "mdd_pct": 7.254700205265991,
        "final_eq": 10290.867758500492,
        "cost_r": 0.9492373126891831,
        "mc_p5": 8780.035641456921
      },
      "pass_gate1": false,
      "fail_reasons": [
        "Sharpe",
        "MCp5"
      ]
    },
    {
      "tag": "CH.6",
      "asset": "sol",
      "period": "20250105_20250704",
      "regime": "2025-H1",
      "ch_metrics": {
        "trades": 94,
        "sharpe": 1.3189110094683494,
        "mdd_pct": 5.740522888092476,
        "final_eq": 10793.562423628167,
        "cost_r": 0.9554721073989673,
        "mc_p5": 9557.653533948702
      },
      "ce_metrics": {
        "trades": 90,
        "sharpe": 0.6146032087464992,
        "mdd_pct": 7.255090509459324,
        "final_eq": 10372.089565572034,
        "cost_r": 0.9550896297065842,
        "mc_p5": 8946.429402583079
      },
      "pass_gate1": true,
      "fail_reasons": []
    },
    {
      "tag": "CH.7",
      "asset": "btc",
      "period": "20250705_20251231",
      "regime": "2025-H2",
      "ch_metrics": {
        "trades": 49,
        "sharpe": 2.631419125020381,
        "mdd_pct": 1.392408245074338,
        "final_eq": 10405.891506774793,
        "cost_r": 0.9790509526928565,
        "mc_p5": 10029.951831468086
      },
      "ce_metrics": {
        "trades": 92,
        "sharpe": 1.6401712390785785,
        "mdd_pct": 4.967220180643035,
        "final_eq": 10513.064634831964,
        "cost_r": 0.9556179350539563,
        "mc_p5": 9795.797468625504
      },
      "pass_gate1": true,
      "fail_reasons": []
    },
    {
      "tag": "CH.8",
      "asset": "eth",
      "period": "20250705_20251231",
      "regime": "2025-H2",
      "ch_metrics": {
        "trades": 77,
        "sharpe": 0.8093431335310273,
        "mdd_pct": 5.967569810201114,
        "final_eq": 10296.002842268079,
        "cost_r": 0.9608405349293117,
        "mc_p5": 9376.41284969111
      },
      "ce_metrics": {
        "trades": 84,
        "sharpe": 1.1471399066784365,
        "mdd_pct": 8.570018852986843,
        "final_eq": 10567.646665014388,
        "cost_r": 0.9572182700996001,
        "mc_p5": 9297.637371793382
      },
      "pass_gate1": false,
      "fail_reasons": [
        "Sharpe",
        "MCp5"
      ]
    },
    {
      "tag": "CH.9",
      "asset": "sol",
      "period": "20250705_20251231",
      "regime": "2025-H2",
      "ch_metrics": {
        "trades": 80,
        "sharpe": 1.9184174648554488,
        "mdd_pct": 4.565911451818832,
        "final_eq": 10951.02255401468,
        "cost_r": 0.9619690955858128,
        "mc_p5": 9776.647663962693
      },
      "ce_metrics": {
        "trades": 86,
        "sharpe": 2.3000391903740414,
        "mdd_pct": 5.128598769287521,
        "final_eq": 11380.532070350757,
        "cost_r": 0.9621405472590615,
        "mc_p5": 9897.849361268905
      },
      "pass_gate1": true,
      "fail_reasons": []
    }
  ]
}