[
  {
    "tag": "MA01.01",
    "rid": "t1ma-10-30-eth-2024h2-long-10m",
    "label": "ETH 2024-H2",
    "params": "10/30",
    "bh_pct": 0.0,
    "alpha": -5.847051884899024,
    "gate_sh": false,
    "gate_alfa": false,
    "trades": 419,
    "pnl_pct": -5.847051884899024,
    "sharpe": -1.7376634049411748,
    "final_eq": 9415.294811510097
  },
  {
    "tag": "MA01.02",
    "rid": "t1ma-10-30-eth-2025h1-long-10m",
    "label": "ETH 2025-H1",
    "params": "10/30",
    "bh_pct": -47.0,
    "alpha": 19.331310871259667,
    "gate_sh": false,
    "gate_alfa": true,
    "trades": 420,
    "pnl_pct": -4.168689128740333,
    "sharpe": -0.9050379585834611,
    "final_eq": 9583.131087125967
  },
  {
    "tag": "MA01.03",
    "rid": "t1ma-10-30-eth-2025h2-long-10m",
    "label": "ETH 2025-H2",
    "params": "10/30",
    "bh_pct": 70.0,
    "alpha": -47.68363772589686,
    "gate_sh": false,
    "gate_alfa": false,
    "trades": 430,
    "pnl_pct": -12.683637725896856,
    "sharpe": -3.7928435309314223,
    "final_eq": 8731.636227410314
  },
  {
    "tag": "MA01.04",
    "rid": "t1ma-10-30-sol-2024h2-long-10m",
    "label": "SOL 2024-H2",
    "params": "10/30",
    "bh_pct": 46.0,
    "alpha": -28.359314082024124,
    "gate_sh": false,
    "gate_alfa": false,
    "trades": 410,
    "pnl_pct": -5.359314082024125,
    "sharpe": -1.209527296155648,
    "final_eq": 9464.068591797588
  },
  {
    "tag": "MA01.05",
    "rid": "t1ma-10-30-sol-2025h1-long-10m",
    "label": "SOL 2025-H1",
    "params": "10/30",
    "bh_pct": -40.0,
    "alpha": 15.663512310141263,
    "gate_sh": false,
    "gate_alfa": true,
    "trades": 390,
    "pnl_pct": -4.336487689858737,
    "sharpe": -0.7973299480468137,
    "final_eq": 9566.351231014127
  },
  {
    "tag": "MA01.06",
    "rid": "t1ma-10-30-sol-2025h2-long-10m",
    "label": "SOL 2025-H2",
    "params": "10/30",
    "bh_pct": 35.0,
    "alpha": -27.56588927302675,
    "gate_sh": false,
    "gate_alfa": false,
    "trades": 418,
    "pnl_pct": -10.065889273026752,
    "sharpe": -2.5322158967258623,
    "final_eq": 8993.411072697325
  },
  {
    "tag": "MA01.07",
    "rid": "t1ma-15-45-eth-2024h2-long-10m",
    "label": "ETH 2024-H2",
    "params": "15/45",
    "bh_pct": 0.0,
    "alpha": -4.72237069240371,
    "gate_sh": false,
    "gate_alfa": false,
    "trades": 265,
    "pnl_pct": -4.72237069240371,
    "sharpe": -1.3653700523079075,
    "final_eq": 9527.762930759629
  },
  {
    "tag": "MA01.08",
    "rid": "t1ma-15-45-eth-2025h1-long-10m",
    "label": "ETH 2025-H1",
    "params": "15/45",
    "bh_pct": -47.0,
    "alpha": 27.45803122755025,
    "gate_sh": false,
    "gate_alfa": true,
    "trades": 264,
    "pnl_pct": 3.9580312275502516,
    "sharpe": 0.9799603762476041,
    "final_eq": 10395.803122755025
  },
  {
    "tag": "MA01.09",
    "rid": "t1ma-15-45-eth-2025h2-long-10m",
    "label": "ETH 2025-H2",
    "params": "15/45",
    "bh_pct": 70.0,
    "alpha": -40.627898583860514,
    "gate_sh": false,
    "gate_alfa": false,
    "trades": 284,
    "pnl_pct": -5.627898583860514,
    "sharpe": -1.6153292325219804,
    "final_eq": 9437.210141613949
  },
  {
    "tag": "MA01.10",
    "rid": "t1ma-15-45-sol-2024h2-long-10m",
    "label": "SOL 2024-H2",
    "params": "15/45",
    "bh_pct": 46.0,
    "alpha": -29.38640930418789,
    "gate_sh": false,
    "gate_alfa": false,
    "trades": 263,
    "pnl_pct": -6.3864093041878895,
    "sharpe": -1.4577756943720634,
    "final_eq": 9361.35906958121
  }
]